{"shotsData": {"h": [{"id": "33094", "minute": "8", "result": "MissedShots", "X": "0.754000015258789", "Y": "0.5629999923706055", "xG": "0.022632300853729248", "player": "Toni Kroos", "h_a": "h", "player_id": "2369", "situation": "OpenPlay", "season": "2014", "shotType": "RightFoot", "match_id": "5806", "h_team": "Real Madrid", "a_team": "Elche", "h_goals": "5", "a_goals": "1", "date": "2014-09-23 19:00:00", "player_assisted": "Cristiano Ronaldo", "lastAction": "Pass"}, {"id": "33095", "minute": "11", "result": "MissedShots", "X": "0.914000015258789", "Y": "0.500999984741211", "xG": "0.06102930009365082", "player": "Raphael Varane", "h_a": "h", "player_id": "2245", "situation": "SetPiece", "season": "2014", "shotType": "Head", "match_id": "5806", "h_team": "Real Madrid", "a_team": "Elche", "h_goals": "5", "a_goals": "1", "date": "2014-09-23 19:00:00", "player_assisted": "James Rodr\u00edguez", "lastAction": "Aerial"}, {"id": "33099", "minute": "19", "result": "Goal", "X": "0.9009999847412109", "Y": "0.4179999923706055", "xG": "0.05951390042901039", "player": "Gareth Bale", "h_a": "h", "player_id": "2251", "situation": "OpenPlay", "season": "2014", "shotType": "Head", "match_id": "5806", "h_team": "Real Madrid", "a_team": "Elche", "h_goals": "5", "a_goals": "1", "date": "2014-09-23 19:00:00", "player_assisted": "James Rodr\u00edguez", "lastAction": "Cross"}, {"id": "33100", "minute": "27", "result": "Goal", "X": "0.885", "Y": "0.5", "xG": "0.7432780265808105", "player": "Cristiano Ronaldo", "h_a": "h", "player_id": "2371", "situation": "Penalty", "season": "2014", "shotType": "RightFoot", "match_id": "5806", "h_team": "Real Madrid", "a_team": "Elche", "h_goals": "5", "a_goals": "1", "date": "2014-09-23 19:00:00", "player_assisted": null, "lastAction": "Standard"}, {"id": "33101", "minute": "31", "result": "Goal", "X": "0.8930000305175781", "Y": "0.46599998474121096", "xG": "0.10987599939107895", "player": "Cristiano Ronaldo", "h_a": "h", "player_id": "2371", "situation": "OpenPlay", "season": "2014", "shotType": "Head", "match_id": "5806", "h_team": "Real Madrid", "a_team": "Elche", "h_goals": "5", "a_goals": "1", "date": "2014-09-23 19:00:00", "player_assisted": "Marcelo", "lastAction": "Cross"}, {"id": "33102", "minute": "34", "result": "MissedShots", "X": "0.7480000305175781", "Y": "0.4229999923706055", "xG": "0.02662930078804493", "player": "James Rodr\u00edguez", "h_a": "h", "player_id": "2249", "situation": "OpenPlay", "season": "2014", "shotType": "LeftFoot", "match_id": "5806", "h_team": "Real Madrid", "a_team": "Elche", "h_goals": "5", "a_goals": "1", "date": "2014-09-23 19:00:00", "player_assisted": "Cristiano Ronaldo", "lastAction": "Pass"}, {"id": "33103", "minute": "36", "result": "SavedShot", "X": "0.750999984741211", "Y": "0.695", "xG": "0.050864800810813904", "player": "Cristiano Ronaldo", "h_a": "h", "player_id": "2371", "situation": "DirectFreekick", "season": "2014", "shotType": "RightFoot", "match_id": "5806", "h_team": "Real Madrid", "a_team": "Elche", "h_goals": "5", "a_goals": "1", "date": "2014-09-23 19:00:00", "player_assisted": null, "lastAction": "Standard"}, {"id": "33104", "minute": "36", "result": "BlockedShot", "X": "0.8730000305175781", "Y": "0.6519999694824219", "xG": "0.11115500330924988", "player": "Isco", "h_a": "h", "player_id": "2255", "situation": "OpenPlay", "season": "2014", "shotType": "LeftFoot", "match_id": "5806", "h_team": "Real Madrid", "a_team": "Elche", "h_goals": "5", "a_goals": "1", "date": "2014-09-23 19:00:00", "player_assisted": "Cristiano Ronaldo", "lastAction": "Pass"}, {"id": "33105", "minute": "37", "result": "SavedShot", "X": "0.855", "Y": "0.4620000076293945", "xG": "0.12362799793481827", "player": "Toni Kroos", "h_a": "h", "player_id": "2369", "situation": "OpenPlay", "season": "2014", "shotType": "LeftFoot", "match_id": "5806", "h_team": "Real Madrid", "a_team": "Elche", "h_goals": "5", "a_goals": "1", "date": "2014-09-23 19:00:00", "player_assisted": "James Rodr\u00edguez", "lastAction": "Pass"}, {"id": "33106", "minute": "38", "result": "SavedShot", "X": "0.7969999694824219", "Y": "0.305", "xG": "0.029534200206398964", "player": "Cristiano Ronaldo", "h_a": "h", "player_id": "2371", "situation": "OpenPlay", "season": "2014", "shotType": "LeftFoot", "match_id": "5806", "h_team": "Real Madrid", "a_team": "Elche", "h_goals": "5", "a_goals": "1", "date": "2014-09-23 19:00:00", "player_assisted": "Daniel Carvajal", "lastAction": "Pass"}, {"id": "33107", "minute": "43", "result": "SavedShot", "X": "0.9169999694824219", "Y": "0.4879999923706055", "xG": "0.3279019892215729", "player": "Sergio Ramos", "h_a": "h", "player_id": "2246", "situation": "FromCorner", "season": "2014", "shotType": "Head", "match_id": "5806", "h_team": "Real Madrid", "a_team": "Elche", "h_goals": "5", "a_goals": "1", "date": "2014-09-23 19:00:00", "player_assisted": "James Rodr\u00edguez", "lastAction": "Cross"}, {"id": "33108", "minute": "47", "result": "MissedShots", "X": "0.89", "Y": "0.43099998474121093", "xG": "0.04152990132570267", "player": "Gareth Bale", "h_a": "h", "player_id": "2251", "situation": "OpenPlay", "season": "2014", "shotType": "Head", "match_id": "5806", "h_team": "Real Madrid", "a_team": "Elche", "h_goals": "5", "a_goals": "1", "date": "2014-09-23 19:00:00", "player_assisted": "Daniel Carvajal", "lastAction": "Cross"}, {"id": "33109", "minute": "49", "result": "BlockedShot", "X": "0.7269999694824218", "Y": "0.5629999923706055", "xG": "0.020026499405503273", "player": "Cristiano Ronaldo", "h_a": "h", "player_id": "2371", "situation": "OpenPlay", "season": "2014", "shotType": "RightFoot", "match_id": "5806", "h_team": "Real Madrid", "a_team": "Elche", "h_goals": "5", "a_goals": "1", "date": "2014-09-23 19:00:00", "player_assisted": "Isco", "lastAction": "Pass"}, {"id": "33110", "minute": "50", "result": "MissedShots", "X": "0.769000015258789", "Y": "0.5029999923706054", "xG": "0.02262520045042038", "player": "Toni Kroos", "h_a": "h", "player_id": "2369", "situation": "FromCorner", "season": "2014", "shotType": "LeftFoot", "match_id": "5806", "h_team": "Real Madrid", "a_team": "Elche", "h_goals": "5", "a_goals": "1", "date": "2014-09-23 19:00:00", "player_assisted": null, "lastAction": "None"}, {"id": "33112", "minute": "51", "result": "MissedShots", "X": "0.9459999847412109", "Y": "0.68", "xG": "0.10029400140047073", "player": "Cristiano Ronaldo", "h_a": "h", "player_id": "2371", "situation": "OpenPlay", "season": "2014", "shotType": "RightFoot", "match_id": "5806", "h_team": "Real Madrid", "a_team": "Elche", "h_goals": "5", "a_goals": "1", "date": "2014-09-23 19:00:00", "player_assisted": "Isco", "lastAction": "Pass"}, {"id": "33116", "minute": "65", "result": "SavedShot", "X": "0.9230000305175782", "Y": "0.7519999694824219", "xG": "0.10710500180721283", "player": "Cristiano Ronaldo", "h_a": "h", "player_id": "2371", "situation": "DirectFreekick", "season": "2014", "shotType": "RightFoot", "match_id": "5806", "h_team": "Real Madrid", "a_team": "Elche", "h_goals": "5", "a_goals": "1", "date": "2014-09-23 19:00:00", "player_assisted": null, "lastAction": "Standard"}, {"id": "33117", "minute": "71", "result": "SavedShot", "X": "0.91", "Y": "0.4640000152587891", "xG": "0.10398399829864502", "player": "Cristiano Ronaldo", "h_a": "h", "player_id": "2371", "situation": "OpenPlay", "season": "2014", "shotType": "Head", "match_id": "5806", "h_team": "Real Madrid", "a_team": "Elche", "h_goals": "5", "a_goals": "1", "date": "2014-09-23 19:00:00", "player_assisted": "James Rodr\u00edguez", "lastAction": "Cross"}, {"id": "33119", "minute": "79", "result": "Goal", "X": "0.885", "Y": "0.5", "xG": "0.7432780265808105", "player": "Cristiano Ronaldo", "h_a": "h", "player_id": "2371", "situation": "Penalty", "season": "2014", "shotType": "RightFoot", "match_id": "5806", "h_team": "Real Madrid", "a_team": "Elche", "h_goals": "5", "a_goals": "1", "date": "2014-09-23 19:00:00", "player_assisted": null, "lastAction": "Standard"}, {"id": "33120", "minute": "82", "result": "ShotOnPost", "X": "0.855999984741211", "Y": "0.49", "xG": "0.31309598684310913", "player": "Toni Kroos", "h_a": "h", "player_id": "2369", "situation": "OpenPlay", "season": "2014", "shotType": "RightFoot", "match_id": "5806", "h_team": "Real Madrid", "a_team": "Elche", "h_goals": "5", "a_goals": "1", "date": "2014-09-23 19:00:00", "player_assisted": "\u00c1lvaro Arbeloa", "lastAction": "Cross"}, {"id": "33121", "minute": "85", "result": "MissedShots", "X": "0.8590000152587891", "Y": "0.505", "xG": "0.12801599502563477", "player": "Chicharito", "h_a": "h", "player_id": "191", "situation": "OpenPlay", "season": "2014", "shotType": "RightFoot", "match_id": "5806", "h_team": "Real Madrid", "a_team": "Elche", "h_goals": "5", "a_goals": "1", "date": "2014-09-23 19:00:00", "player_assisted": "Gareth Bale", "lastAction": "Pass"}, {"id": "33122", "minute": "86", "result": "BlockedShot", "X": "0.7609999847412109", "Y": "0.4329999923706055", "xG": "0.04171010106801987", "player": "Gareth Bale", "h_a": "h", "player_id": "2251", "situation": "OpenPlay", "season": "2014", "shotType": "LeftFoot", "match_id": "5806", "h_team": "Real Madrid", "a_team": "Elche", "h_goals": "5", "a_goals": "1", "date": "2014-09-23 19:00:00", "player_assisted": "Toni Kroos", "lastAction": "Pass"}, {"id": "33123", "minute": "87", "result": "SavedShot", "X": "0.9640000152587891", "Y": "0.435", "xG": "0.14309899508953094", "player": "Cristiano Ronaldo", "h_a": "h", "player_id": "2371", "situation": "OpenPlay", "season": "2014", "shotType": "Head", "match_id": "5806", "h_team": "Real Madrid", "a_team": "Elche", "h_goals": "5", "a_goals": "1", "date": "2014-09-23 19:00:00", "player_assisted": "Marcelo", "lastAction": "Cross"}, {"id": "33125", "minute": "91", "result": "Goal", "X": "0.8880000305175781", "Y": "0.534000015258789", "xG": "0.5070469975471497", "player": "Cristiano Ronaldo", "h_a": "h", "player_id": "2371", "situation": "OpenPlay", "season": "2014", "shotType": "RightFoot", "match_id": "5806", "h_team": "Real Madrid", "a_team": "Elche", "h_goals": "5", "a_goals": "1", "date": "2014-09-23 19:00:00", "player_assisted": "Gareth Bale", "lastAction": "Throughball"}], "a": [{"id": "33093", "minute": "4", "result": "SavedShot", "X": "0.7609999847412109", "Y": "0.6709999847412109", "xG": "0.06032729893922806", "player": "Edu Alb\u00e1car", "h_a": "a", "player_id": "4109", "situation": "DirectFreekick", "season": "2014", "shotType": "LeftFoot", "match_id": "5806", "h_team": "Real Madrid", "a_team": "Elche", "h_goals": "5", "a_goals": "1", "date": "2014-09-23 19:00:00", "player_assisted": null, "lastAction": "Standard"}, {"id": "33096", "minute": "13", "result": "BlockedShot", "X": "0.8680000305175781", "Y": "0.58", "xG": "0.04359839856624603", "player": "V\u00edctor Rodr\u00edguez", "h_a": "a", "player_id": "2471", "situation": "FromCorner", "season": "2014", "shotType": "LeftFoot", "match_id": "5806", "h_team": "Real Madrid", "a_team": "Elche", "h_goals": "5", "a_goals": "1", "date": "2014-09-23 19:00:00", "player_assisted": "Edu Alb\u00e1car", "lastAction": "Cross"}, {"id": "33097", "minute": "14", "result": "Goal", "X": "0.885", "Y": "0.5", "xG": "0.7432780265808105", "player": "Edu Alb\u00e1car", "h_a": "a", "player_id": "4109", "situation": "Penalty", "season": "2014", "shotType": "LeftFoot", "match_id": "5806", "h_team": "Real Madrid", "a_team": "Elche", "h_goals": "5", "a_goals": "1", "date": "2014-09-23 19:00:00", "player_assisted": null, "lastAction": "Standard"}, {"id": "33098", "minute": "17", "result": "MissedShots", "X": "0.8140000152587891", "Y": "0.23100000381469726", "xG": "0.06034550070762634", "player": "Edu Alb\u00e1car", "h_a": "a", "player_id": "4109", "situation": "DirectFreekick", "season": "2014", "shotType": "LeftFoot", "match_id": "5806", "h_team": "Real Madrid", "a_team": "Elche", "h_goals": "5", "a_goals": "1", "date": "2014-09-23 19:00:00", "player_assisted": null, "lastAction": "Standard"}, {"id": "33111", "minute": "50", "result": "MissedShots", "X": "0.879000015258789", "Y": "0.29", "xG": "0.03327219933271408", "player": "Coro", "h_a": "a", "player_id": "4112", "situation": "OpenPlay", "season": "2014", "shotType": "RightFoot", "match_id": "5806", "h_team": "Real Madrid", "a_team": "Elche", "h_goals": "5", "a_goals": "1", "date": "2014-09-23 19:00:00", "player_assisted": "Domingo Cisma", "lastAction": "Pass"}, {"id": "33113", "minute": "55", "result": "MissedShots", "X": "0.7719999694824219", "Y": "0.6980000305175781", "xG": "0.0173506997525692", "player": "Pedro Mosquera", "h_a": "a", "player_id": "2320", "situation": "OpenPlay", "season": "2014", "shotType": "LeftFoot", "match_id": "5806", "h_team": "Real Madrid", "a_team": "Elche", "h_goals": "5", "a_goals": "1", "date": "2014-09-23 19:00:00", "player_assisted": "Adri\u00e1n", "lastAction": "Pass"}, {"id": "33114", "minute": "61", "result": "BlockedShot", "X": "0.735999984741211", "Y": "0.34700000762939454", "xG": "0.050462301820516586", "player": "Edu Alb\u00e1car", "h_a": "a", "player_id": "4109", "situation": "DirectFreekick", "season": "2014", "shotType": "LeftFoot", "match_id": "5806", "h_team": "Real Madrid", "a_team": "Elche", "h_goals": "5", "a_goals": "1", "date": "2014-09-23 19:00:00", "player_assisted": null, "lastAction": "Standard"}, {"id": "33115", "minute": "62", "result": "SavedShot", "X": "0.955999984741211", "Y": "0.415", "xG": "0.039956800639629364", "player": "Lomb\u00e1n", "h_a": "a", "player_id": "2085", "situation": "FromCorner", "season": "2014", "shotType": "Head", "match_id": "5806", "h_team": "Real Madrid", "a_team": "Elche", "h_goals": "5", "a_goals": "1", "date": "2014-09-23 19:00:00", "player_assisted": "Faycal Fajr", "lastAction": "Aerial"}, {"id": "33118", "minute": "73", "result": "MissedShots", "X": "0.7230000305175781", "Y": "0.3290000152587891", "xG": "0.008043830282986164", "player": "Jonathas", "h_a": "a", "player_id": "2480", "situation": "OpenPlay", "season": "2014", "shotType": "RightFoot", "match_id": "5806", "h_team": "Real Madrid", "a_team": "Elche", "h_goals": "5", "a_goals": "1", "date": "2014-09-23 19:00:00", "player_assisted": null, "lastAction": "None"}, {"id": "33124", "minute": "90", "result": "MissedShots", "X": "0.759000015258789", "Y": "0.35900001525878905", "xG": "0.01783899962902069", "player": "Pedro Mosquera", "h_a": "a", "player_id": "2320", "situation": "OpenPlay", "season": "2014", "shotType": "LeftFoot", "match_id": "5806", "h_team": "Real Madrid", "a_team": "Elche", "h_goals": "5", "a_goals": "1", "date": "2014-09-23 19:00:00", "player_assisted": "Domingo Cisma", "lastAction": "Pass"}]}, "match_info": {"id": "5806", "fid": "862085", "h": "150", "a": "207", "date": "2014-09-23 19:00:00", "league_id": "4", "season": "2014", "h_goals": "5", "a_goals": "1", "team_h": "Real Madrid", "team_a": "Elche", "h_xg": "3.93785", "a_xg": "1.07447", "h_w": "0.9313", "h_d": "0.0543", "h_l": "0.0144", "league": "La liga", "h_shot": "23", "a_shot": "10", "h_shotOnTarget": "12", "a_shotOnTarget": "3", "h_deep": "8", "a_deep": "0", "a_ppda": "23.9412", "h_ppda": "10.2609"}, "rostersData": {"h": {"36841": {"id": "36841", "goals": "0", "own_goals": "0", "shots": "0", "xG": "0", "time": "90", "player_id": "2243", "team_id": "150", "position": "GK", "player": "Keylor Navas", "h_a": "h", "yellow_card": "0", "red_card": "0", "roster_in": "0", "roster_out": "0", "key_passes": "0", "assists": "0", "xA": "0", "xGChain": "0.6073409914970398", "xGBuildup": "0.6073409914970398", "positionOrder": "1"}, "36842": {"id": "36842", "goals": "0", "own_goals": "0", "shots": "0", "xG": "0", "time": "66", "player_id": "2260", "team_id": "150", "position": "DR", "player": "Daniel Carvajal", "h_a": "h", "yellow_card": "1", "red_card": "0", "roster_in": "36853", "roster_out": "0", "key_passes": "2", "assists": "0", "xA": "0.07106409966945648", "xGChain": "0.351610004901886", "xGBuildup": "0.351610004901886", "positionOrder": "2"}, "36844": {"id": "36844", "goals": "0", "own_goals": "0", "shots": "1", "xG": "0.3279019892215729", "time": "83", "player_id": "2246", "team_id": "150", "position": "DC", "player": "Sergio Ramos", "h_a": "h", "yellow_card": "0", "red_card": "0", "roster_in": "36854", "roster_out": "0", "key_passes": "0", "assists": "0", "xA": "0", "xGChain": "0.2682119905948639", "xGBuildup": "0.2682119905948639", "positionOrder": "3"}, "36843": {"id": "36843", "goals": "0", "own_goals": "0", "shots": "1", "xG": "0.06102930009365082", "time": "90", "player_id": "2245", "team_id": "150", "position": "DC", "player": "Raphael Varane", "h_a": "h", "yellow_card": "0", "red_card": "0", "roster_in": "0", "roster_out": "0", "key_passes": "0", "assists": "0", "xA": "0", "xGChain": "0.09369630366563797", "xGBuildup": "0.09369630366563797", "positionOrder": "3"}, "36845": {"id": "36845", "goals": "0", "own_goals": "0", "shots": "0", "xG": "0", "time": "90", "player_id": "2257", "team_id": "150", "position": "DL", "player": "Marcelo", "h_a": "h", "yellow_card": "1", "red_card": "0", "roster_in": "0", "roster_out": "0", "key_passes": "2", "assists": "1", "xA": "0.2529749870300293", "xGChain": "0.5139849781990051", "xGBuildup": "0.3708859980106354", "positionOrder": "4"}, "36846": {"id": "36846", "goals": "0", "own_goals": "0", "shots": "1", "xG": "0.02662930078804493", "time": "79", "player_id": "2249", "team_id": "150", "position": "MR", "player": "James Rodr\u00edguez", "h_a": "h", "yellow_card": "0", "red_card": "0", "roster_in": "36852", "roster_out": "0", "key_passes": "5", "assists": "1", "xA": "0.676056981086731", "xGChain": "0.4946950078010559", "xGBuildup": "0.2849240005016327", "positionOrder": "8"}, "36847": {"id": "36847", "goals": "0", "own_goals": "0", "shots": "4", "xG": "0.4819819927215576", "time": "90", "player_id": "2369", "team_id": "150", "position": "MC", "player": "Toni Kroos", "h_a": "h", "yellow_card": "0", "red_card": "0", "roster_in": "0", "roster_out": "0", "key_passes": "2", "assists": "0", "xA": "0.04171010106801987", "xGChain": "0.9511579871177673", "xGBuildup": "0.45009100437164307", "positionOrder": "9"}, "36848": {"id": "36848", "goals": "0", "own_goals": "0", "shots": "0", "xG": "0", "time": "90", "player_id": "2232", "team_id": "150", "position": "MC", "player": "Asier Illarramendi", "h_a": "h", "yellow_card": "0", "red_card": "0", "roster_in": "0", "roster_out": "0", "key_passes": "0", "assists": "0", "xA": "0", "xGChain": "1.1931699514389038", "xGBuildup": "1.1931699514389038", "positionOrder": "9"}, "36849": {"id": "36849", "goals": "0", "own_goals": "0", "shots": "1", "xG": "0.11115500330924988", "time": "90", "player_id": "2255", "team_id": "150", "position": "ML", "player": "Isco", "h_a": "h", "yellow_card": "0", "red_card": "0", "roster_in": "0", "roster_out": "0", "key_passes": "2", "assists": "0", "xA": "0.12032099813222885", "xGChain": "1.1031800508499146", "xGBuildup": "0.8917289972305298", "positionOrder": "10"}, "36850": {"id": "36850", "goals": "4", "own_goals": "0", "shots": "11", "xG": "2.6583900451660156", "time": "90", "player_id": "2371", "team_id": "150", "position": "FW", "player": "Cristiano Ronaldo", "h_a": "h", "yellow_card": "0", "red_card": "0", "roster_in": "0", "roster_out": "0", "key_passes": "3", "assists": "0", "xA": "0.16041700541973114", "xGChain": "1.3989499807357788", "xGBuildup": "0.27423200011253357", "positionOrder": "15"}, "36851": {"id": "36851", "goals": "1", "own_goals": "0", "shots": "3", "xG": "0.14275400340557098", "time": "90", "player_id": "2251", "team_id": "150", "position": "FW", "player": "Gareth Bale", "h_a": "h", "yellow_card": "0", "red_card": "0", "roster_in": "0", "roster_out": "0", "key_passes": "2", "assists": "1", "xA": "0.6350629925727844", "xGChain": "0.7778170108795166", "xGBuildup": "0", "positionOrder": "15"}, "36853": {"id": "36853", "goals": "0", "own_goals": "0", "shots": "0", "xG": "0", "time": "24", "player_id": "1704", "team_id": "150", "position": "Sub", "player": "\u00c1lvaro Arbeloa", "h_a": "h", "yellow_card": "0", "red_card": "0", "roster_in": "0", "roster_out": "36842", "key_passes": "1", "assists": "0", "xA": "0.31309598684310913", "xGChain": "0.41707998514175415", "xGBuildup": "0.10398399829864502", "positionOrder": "17"}, "36854": {"id": "36854", "goals": "0", "own_goals": "0", "shots": "0", "xG": "0", "time": "7", "player_id": "2247", "team_id": "150", "position": "Sub", "player": "Nacho", "h_a": "h", "yellow_card": "0", "red_card": "0", "roster_in": "0", "roster_out": "36844", "key_passes": "0", "assists": "0", "xA": "0", "xGChain": "0.04171010106801987", "xGBuildup": "0.04171010106801987", "positionOrder": "17"}, "36852": {"id": "36852", "goals": "0", "own_goals": "0", "shots": "1", "xG": "0.12801599502563477", "time": "11", "player_id": "191", "team_id": "150", "position": "Sub", "player": "Chicharito", "h_a": "h", "yellow_card": "0", "red_card": "0", "roster_in": "0", "roster_out": "36846", "key_passes": "0", "assists": "0", "xA": "0", "xGChain": "0.4411120116710663", "xGBuildup": "0.31309598684310913", "positionOrder": "17"}}, "a": {"36855": {"id": "36855", "goals": "0", "own_goals": "0", "shots": "0", "xG": "0", "time": "90", "player_id": "4115", "team_id": "207", "position": "GK", "player": "Manu Herrera", "h_a": "a", "yellow_card": "0", "red_card": "0", "roster_in": "0", "roster_out": "0", "key_passes": "0", "assists": "0", "xA": "0", "xGChain": "0", "xGBuildup": "0", "positionOrder": "1"}, "36856": {"id": "36856", "goals": "0", "own_goals": "0", "shots": "0", "xG": "0", "time": "90", "player_id": "4114", "team_id": "207", "position": "DR", "player": "Domingo Cisma", "h_a": "a", "yellow_card": "0", "red_card": "0", "roster_in": "0", "roster_out": "0", "key_passes": "2", "assists": "0", "xA": "0.05111119896173477", "xGChain": "0.05111119896173477", "xGBuildup": "0", "positionOrder": "2"}, "36857": {"id": "36857", "goals": "0", "own_goals": "0", "shots": "0", "xG": "0", "time": "90", "player_id": "4116", "team_id": "207", "position": "DC", "player": "Sergio Pelegr\u00edn", "h_a": "a", "yellow_card": "0", "red_card": "0", "roster_in": "0", "roster_out": "0", "key_passes": "0", "assists": "0", "xA": "0", "xGChain": "0.01783899962902069", "xGBuildup": "0.01783899962902069", "positionOrder": "3"}, "36858": {"id": "36858", "goals": "0", "own_goals": "0", "shots": "1", "xG": "0.039956800639629364", "time": "90", "player_id": "2085", "team_id": "207", "position": "DC", "player": "Lomb\u00e1n", "h_a": "a", "yellow_card": "0", "red_card": "0", "roster_in": "0", "roster_out": "0", "key_passes": "0", "assists": "0", "xA": "0", "xGChain": "0", "xGBuildup": "0", "positionOrder": "3"}, "36859": {"id": "36859", "goals": "1", "own_goals": "0", "shots": "4", "xG": "0.9144129753112793", "time": "90", "player_id": "4109", "team_id": "207", "position": "DL", "player": "Edu Alb\u00e1car", "h_a": "a", "yellow_card": "1", "red_card": "0", "roster_in": "0", "roster_out": "0", "key_passes": "1", "assists": "0", "xA": "0.04359839856624603", "xGChain": "0.03327219933271408", "xGBuildup": "0.03327219933271408", "positionOrder": "4"}, "36861": {"id": "36861", "goals": "0", "own_goals": "0", "shots": "2", "xG": "0.03518969938158989", "time": "90", "player_id": "2320", "team_id": "207", "position": "DMC", "player": "Pedro Mosquera", "h_a": "a", "yellow_card": "0", "red_card": "0", "roster_in": "0", "roster_out": "0", "key_passes": "0", "assists": "0", "xA": "0", "xGChain": "0.06846190243959427", "xGBuildup": "0.03327219933271408", "positionOrder": "7"}, "36860": {"id": "36860", "goals": "0", "own_goals": "0", "shots": "0", "xG": "0", "time": "68", "player_id": "2133", "team_id": "207", "position": "DMC", "player": "Adri\u00e1n", "h_a": "a", "yellow_card": "0", "red_card": "0", "roster_in": "36866", "roster_out": "0", "key_passes": "1", "assists": "0", "xA": "0.0173506997525692", "xGChain": "0.05062289908528328", "xGBuildup": "0.03327219933271408", "positionOrder": "7"}, "36862": {"id": "36862", "goals": "0", "own_goals": "0", "shots": "0", "xG": "0", "time": "79", "player_id": "4111", "team_id": "207", "position": "AMR", "player": "Rodrigues", "h_a": "a", "yellow_card": "0", "red_card": "0", "roster_in": "36868", "roster_out": "0", "key_passes": "0", "assists": "0", "xA": "0", "xGChain": "0.05062289908528328", "xGBuildup": "0.05062289908528328", "positionOrder": "11"}, "36863": {"id": "36863", "goals": "0", "own_goals": "0", "shots": "1", "xG": "0.04359839856624603", "time": "90", "player_id": "2471", "team_id": "207", "position": "AMC", "player": "V\u00edctor Rodr\u00edguez", "h_a": "a", "yellow_card": "0", "red_card": "0", "roster_in": "0", "roster_out": "0", "key_passes": "0", "assists": "0", "xA": "0", "xGChain": "0.05111119896173477", "xGBuildup": "0.05111119896173477", "positionOrder": "12"}, "36864": {"id": "36864", "goals": "0", "own_goals": "0", "shots": "1", "xG": "0.03327219933271408", "time": "62", "player_id": "4112", "team_id": "207", "position": "AML", "player": "Coro", "h_a": "a", "yellow_card": "0", "red_card": "0", "roster_in": "36867", "roster_out": "0", "key_passes": "0", "assists": "0", "xA": "0", "xGChain": "0.05062289908528328", "xGBuildup": "0.0173506997525692", "positionOrder": "13"}, "36865": {"id": "36865", "goals": "0", "own_goals": "0", "shots": "1", "xG": "0.008043830282986164", "time": "90", "player_id": "2480", "team_id": "207", "position": "FW", "player": "Jonathas", "h_a": "a", "yellow_card": "0", "red_card": "0", "roster_in": "0", "roster_out": "0", "key_passes": "0", "assists": "0", "xA": "0", "xGChain": "0.0253944993019104", "xGBuildup": "0.0173506997525692", "positionOrder": "15"}, "36867": {"id": "36867", "goals": "0", "own_goals": "0", "shots": "0", "xG": "0", "time": "28", "player_id": "2319", "team_id": "207", "position": "Sub", "player": "Faycal Fajr", "h_a": "a", "yellow_card": "0", "red_card": "0", "roster_in": "0", "roster_out": "36864", "key_passes": "1", "assists": "0", "xA": "0.039956800639629364", "xGChain": "0.01783899962902069", "xGBuildup": "0.01783899962902069", "positionOrder": "17"}, "36868": {"id": "36868", "goals": "0", "own_goals": "0", "shots": "0", "xG": "0", "time": "11", "player_id": "4113", "team_id": "207", "position": "Sub", "player": "Cristian Herrera", "h_a": "a", "yellow_card": "0", "red_card": "0", "roster_in": "0", "roster_out": "36862", "key_passes": "0", "assists": "0", "xA": "0", "xGChain": "0", "xGBuildup": "0", "positionOrder": "17"}, "36866": {"id": "36866", "goals": "0", "own_goals": "0", "shots": "0", "xG": "0", "time": "22", "player_id": "1134", "team_id": "207", "position": "Sub", "player": "Mario Pasalic", "h_a": "a", "yellow_card": "0", "red_card": "0", "roster_in": "0", "roster_out": "36860", "key_passes": "0", "assists": "0", "xA": "0", "xGChain": "0.01783899962902069", "xGBuildup": "0.01783899962902069", "positionOrder": "17"}}}}